pyprinter/__init__.py
pyprinter/file_size.py
pyprinter/printer.py
pyprinter/progress_bar.py
pyprinter/table.py
pyprinter/external/__init__.py
pyprinter/external/prettytable.py
pyprinter-1.5.3.dist-info/LICENSE
pyprinter-1.5.3.dist-info/METADATA
pyprinter-1.5.3.dist-info/WHEEL
pyprinter-1.5.3.dist-info/top_level.txt
pyprinter-1.5.3.dist-info/RECORD
