Metadata-Version: 2.1
Name: pyprinter
Version: 1.5.3
Summary: Print Everything!
Home-page: https://github.com/ofir123/py-printer
Author: Ofir Brukner
Author-email: ofirbrukner@gmail.com
License: MIT
Download-URL: https://github.com/ofir123/py-printer/archive/1.5.3.tar.gz
Keywords: Python,Python3,color,print,unicode,encoding
Platform: UNKNOWN
Classifier: Development Status :: 5 - Production/Stable
Classifier: Intended Audience :: Developers
Classifier: Natural Language :: English
Classifier: License :: OSI Approved :: MIT License
Classifier: Programming Language :: Python
Classifier: Programming Language :: Python :: 3
Classifier: Programming Language :: Python :: 3.6
Classifier: Programming Language :: Python :: 3.7
Classifier: Topic :: Software Development :: Libraries
Classifier: Topic :: Utilities
Provides-Extra: test
